nosedep.py
nosedep-0.7.dist-info/DESCRIPTION.rst
nosedep-0.7.dist-info/METADATA
nosedep-0.7.dist-info/RECORD
nosedep-0.7.dist-info/WHEEL
nosedep-0.7.dist-info/entry_points.txt
nosedep-0.7.dist-info/metadata.json
nosedep-0.7.dist-info/top_level.txt
