Metadata-Version: 2.0
Name: nosedep
Version: 0.7
Summary: Nose test dependency support
Home-page: https://github.com/Zitrax/nose-dep
Maintainer: Daniel Bengtsson
Maintainer-email: daniel@bengtssons.info
License: MIT
Platform: UNKNOWN
Classifier: Intended Audience :: Developers
Classifier: Topic :: Software Development :: Testing
Classifier: Programming Language :: Python :: 2.7
Classifier: Programming Language :: Python :: 3.3
Classifier: Programming Language :: Python :: 3.4
Classifier: Programming Language :: Python :: 3.5
Requires-Dist: nose
Requires-Dist: toposort
